[
  {
    "title": "FoodSaverSG",
    "imageSrc": "projects/FoodSaverSG.png",
    "description": "Brainhack Code@Exp • An application that aims to tackle the issue of food wastage in Singapore",
    "skills": [],
    "source": "https://github.com/zhxyu019/FoodSaverSG",
    "feature": ""
  },
  {
    "title": "GiftDuck",
    "imageSrc": "projects/giftduck.jpg",
    "description": "SAP'2022 Project • An iOS application published on the App Store that aims to help users remember birthdays",
    "skills": [],
    "source": "https://github.com/DWizard11/GiftHub",
    "feature": "https://apps.apple.com/us/app/giftduck/id6444735527"
  },
  {
    "title": "LifeSync",
    "imageSrc": "projects/lifesync.png",
    "description": "An integrated Medication System that harnesses microneedling technology and an application",
    "skills": [],
    "source": "",
    "feature": "https://www.scs.org.sg/awards/splash/2023/announcement"
  },
  {
    "title": "SolarSoln",
    "imageSrc": "projects/solarsoln.png",
    "description": "IMPACT festival • A solar-powered phone charging device that aims to reduce electricity overconsumption",
    "skills": [],
    "feature": "https://www.instagram.com/p/CbRMkMsKOFT/"
  },
  {
    "title": "Spamshield",
    "imageSrc": "projects/WWDC.png",
    "description": "WWDC'24 Submission • Application built using SwiftUI & CoreML that uses text classification and sentiment analysis to detect harmful spam messages",
    "skills": [],
    "feature": "",
    "source": "https://github.com/zhxyu019/WWDC24App.swiftpm"
  }
]
